[
    {
        "event_name": "Sad Girls Club at UCI",
        "event_link": "https://campusgroups.uci.eduhttps://campusgroups.uci.edu/rsvp?id=1063256",
        "event_id": "1063256",
        "event_date": "Mon, Jun 28, 2021 12:00 AM  Mon, Jul 1, 2024 10:00 AM PDT (GMT-7)",
        "event_location": "Private Location (register to display)",
        "event_tags": [
            "Social",
            "counseling",
            "Sad Girls Club",
            "Selfcare",
            "Virtual"
        ]
    },
    {
        "event_name": "Bohemian of the Arroyo Seco: Idah Meacham Strobridge",
        "event_link": "https://campusgroups.uci.eduhttps://campusgroups.uci.edu/rsvp?id=1928984",
        "event_id": "1928984",
        "event_date": "Sat, Sep 30, 2023 12:00 AM  Sat, Jan 13, 2024 11:00 PM PDT (GMT-7)",
        "event_location": "Langson Institute and Museum of California Art",
        "event_tags": [
            "Cultural",
            "Art",
            "Art exhibition",
            "Culture",
            "UCI Illuminations"
        ]
    },
    {
        "event_name": "E.A.A.T.: Experiments in Art, Access & Technology",
        "event_link": "https://campusgroups.uci.eduhttps://campusgroups.uci.edu/rsvp?id=1928459",
        "event_id": "1928459",
        "event_date": "Sat, Sep 30, 2023 12:00 PM  Sat, Jan 13, 2024 6:00 PM PDT (GMT-7)",
        "event_location": "Beall Center for Art + Technology (parking: Mesa Structure at 4000 Mesa Rd; Irvine, CA 92617)",
        "event_tags": [
            "Ticket Sales",
            "Art",
            "Arts",
            "Exhibit",
            "Gallery"
        ]
    },
    {
        "event_name": "Tai Chi  Beginners",
        "event_link": "https://campusgroups.uci.eduhttps://campusgroups.uci.edu/rsvp?id=1928191",
        "event_id": "1928191",
        "event_date": "Fri, Oct 6, 2023 8:00 AM  Fri, Nov 17, 2023 9:00 AM PDT (GMT-7)",
        "event_location": "UCI Susan Samueli Integrative Health Institute",
        "event_tags": [
            "Workshop",
            "Class",
            "Community",
            "Exercise",
            "Healthcare",
            "Integrative Health",
            "Self Care",
            "Wellness"
        ]
    },
    {
        "event_name": "Think of it as Money! A solo project by Adri Juli",
        "event_link": "https://campusgroups.uci.eduhttps://campusgroups.uci.edu/rsvp?id=1929110",
        "event_id": "1929110",
        "event_date": "Sat, Oct 7, 2023 9:00 AM  Sat, Dec 16, 2023 10:00 AM PDT (GMT-7)",
        "event_location": "Private Location (sign in to display)",
        "event_tags": [
            "Cultural",
            "Art",
            "Art exhibition"
        ]
    },
    {
        "event_name": "Think of it as Money!: A Solo Project by Adri Juli",
        "event_link": "https://campusgroups.uci.eduhttps://campusgroups.uci.edu/rsvp?id=1928472",
        "event_id": "1928472",
        "event_date": "Sat, Oct 7, 2023 12:00 PM  Sat, Dec 16, 2023 6:00 PM PDT (GMT-7)",
        "event_location": "Contemporary Arts Center Gallery (parking: Mesa Structure at 4000 Mesa Rd; Irvine, CA 92617)",
        "event_tags": [
            "Ticket Sales",
            "Art",
            "Arts",
            "Exhibit",
            "Gallery",
            "Media"
        ]
    },
    {
        "event_name": "Affective Resistance",
        "event_link": "https://campusgroups.uci.eduhttps://campusgroups.uci.edu/rsvp?id=1928463",
        "event_id": "1928463",
        "event_date": "Sat, Oct 7, 2023 12:00 PM  Sat, Dec 16, 2023 6:00 PM PDT (GMT-7)",
        "event_location": "University Art Gallery | Room Gallery (parking: Mesa Structure at 4000 Mesa Rd; Irvine, CA 92617)",
        "event_tags": [
            "Ticket Sales",
            "Art",
            "Arts",
            "Exhibit",
            "Gallery"
        ]
    },
    {
        "event_name": "Peter's Quest Series: The Complete Guide to Campus Organization",
        "event_link": "https://campusgroups.uci.eduhttps://campusgroups.uci.edu/rsvp?id=1930014",
        "event_id": "1930014",
        "event_date": "Thu, Oct 12, 2023 1:00 PM  Fri, Jun 7, 2024 1:00 PM PDT (GMT-7)",
        "event_location": "Private Location (sign in to display)",
        "event_tags": [
            "Workshop",
            "COVP"
        ]
    },
    {
        "event_name": "Mindfulness-Based Stress Reduction (MBSR)",
        "event_link": "https://campusgroups.uci.eduhttps://campusgroups.uci.edu/rsvp?id=1929824",
        "event_id": "1929824",
        "event_date": "Mon, Oct 23, 2023 6:00 PM  Mon, Dec 11, 2023 8:00 PM PDT (GMT-7)",
        "event_location": "Private Location (sign in to display)",
        "event_tags": [
            "Educational/Awareness",
            "Class",
            "Integrative Health",
            "meditation",
            "Meditation",
            "Wellness"
        ]
    },
    {
        "event_name": "Finance and Freebies",
        "event_link": "https://campusgroups.uci.eduhttps://campusgroups.uci.edu/rsvp?id=1930515",
        "event_id": "1930515",
        "event_date": "Sun, Nov 5, 2023 2 PM  3 PM PST (GMT-8)",
        "event_location": "Vista del Campo Norte Clubhouse Lobby",
        "event_tags": [
            "Social",
            "ACC"
        ]
    },
    {
        "event_name": "Irvine Barclay Theatre: Ramayana | An Ancient Indian Epic Brought to Life (Students Only)",
        "event_link": "https://campusgroups.uci.eduhttps://campusgroups.uci.edu/rsvp?id=1929072",
        "event_id": "1929072",
        "event_date": "Sun, Nov 5, 2023 4 PM  6 PM PST (GMT-8)",
        "event_location": "Private Location (sign in to display)",
        "event_tags": [
            "Cultural",
            "Arts",
            "Performance"
        ]
    },
    {
        "event_name": "In-Person Testing Appointment - Academic Testing Center",
        "event_link": "https://campusgroups.uci.eduhttps://campusgroups.uci.edu/rsvp?id=1930372",
        "event_id": "1930372",
        "event_date": "Mon, Nov 6, 2023 10 AM  12 PM PST (GMT-8)",
        "event_location": "Academic Testing Center",
        "event_tags": [
            "Academic",
            "Exam",
            "Placement"
        ]
    },
    {
        "event_name": "OAI TUTORING+ PROGRAM - In Person Mondays",
        "event_link": "https://campusgroups.uci.eduhttps://campusgroups.uci.edu/rsvp?id=1930426",
        "event_id": "1930426",
        "event_date": "Mon, Nov 6, 2023 11 AM  12 PM PST (GMT-8)",
        "event_location": "Private Location (sign in to display)",
        "event_tags": [
            "Academic",
            "Computer Science",
            "Data Science",
            "ICS",
            "Informatics",
            "Information and Computer Sciences",
            "Programming",
            "STEM",
            "Technology",
            "Tutors"
        ]
    },
    {
        "event_name": "First-Gen Programs Tabling",
        "event_link": "https://campusgroups.uci.eduhttps://campusgroups.uci.edu/rsvp?id=1930184",
        "event_id": "1930184",
        "event_date": "Mon, Nov 6, 2023 11 AM  1 PM PST (GMT-8)",
        "event_location": "Private Location (sign in to display)",
        "event_tags": [
            "Social",
            "OVPTL-Social Event"
        ]
    },
    {
        "event_name": "Cup of SOAR",
        "event_link": "https://campusgroups.uci.eduhttps://campusgroups.uci.edu/rsvp?id=1929350",
        "event_id": "1929350",
        "event_date": "Mon, Nov 6, 2023 11 AM  1 PM PST (GMT-8)",
        "event_location": "Private Location (sign in to display)",
        "event_tags": [
            "Luncheon",
            "SOAR"
        ]
    },
    {
        "event_name": "RAND Corporation Lunch & Learn",
        "event_link": "https://campusgroups.uci.eduhttps://campusgroups.uci.edu/rsvp?id=1930133",
        "event_id": "1930133",
        "event_date": "Mon, Nov 6, 2023 11:30 AM  2:30 PM PST (GMT-8)",
        "event_location": "Graduate & Postdoctoral Scholar Resource Center - 3100 Gateway Study Center",
        "event_tags": [
            "Workshop",
            "Graduate Students",
            "Postdoctoral Scholars"
        ]
    },
    {
        "event_name": "Monday Garden Volunteer Hours (Shift 1)",
        "event_link": "https://campusgroups.uci.eduhttps://campusgroups.uci.edu/rsvp?id=1930269",
        "event_id": "1930269",
        "event_date": "Mon, Nov 6, 2023 12 PM  2 PM PST (GMT-8)",
        "event_location": "Private Location (sign in to display)",
        "event_tags": [
            "Community Service",
            "Activism",
            "Community",
            "Community Fun",
            "Community Service",
            "Empowerment",
            "Food",
            "FRESH Basic Needs Hub",
            "Gardening",
            "Nature",
            "Relaxation",
            "Social",
            "Social Ecology",
            "Social Justice",
            "Sustainability",
            "Sustainability Resource Center",
            "Traditional",
            "Volunteer",
            "Volunteer Programs",
            "Wellness"
        ]
    },
    {
        "event_name": "NALSA x LLSA Dia de Muertos",
        "event_link": "https://campusgroups.uci.eduhttps://campusgroups.uci.edu/rsvp?id=1930330",
        "event_id": "1930330",
        "event_date": "Mon, Nov 6, 2023 12 PM  1 PM PST (GMT-8)",
        "event_location": "MPAA 420",
        "event_tags": [
            "Meeting",
            "Law - Students"
        ]
    },
    {
        "event_name": "Quick Bites: Healthy Holiday Eating",
        "event_link": "https://campusgroups.uci.eduhttps://campusgroups.uci.edu/rsvp?id=1930320",
        "event_id": "1930320",
        "event_date": "Mon, Nov 6, 2023 12:30 PM  1 PM PST (GMT-8)",
        "event_location": "Online Event",
        "event_tags": [
            "Workshop",
            "Food",
            "Nutrition",
            "Virtual",
            "Wellness"
        ]
    },
    {
        "event_name": "Gateway Initiative Workshop: First-Gen Week Talk - Combatting Imposter Syndrome",
        "event_link": "https://campusgroups.uci.eduhttps://campusgroups.uci.edu/rsvp?id=1929903",
        "event_id": "1929903",
        "event_date": "Mon, Nov 6, 2023 1 PM  1:50 PM PST (GMT-8)",
        "event_location": "Private Location (sign in to display)",
        "event_tags": [
            "Academic",
            "OVPTL-Workshop"
        ]
    },
    {
        "event_name": "Fall Travel/Publication Award Application Deadline",
        "event_link": "https://campusgroups.uci.eduhttps://campusgroups.uci.edu/rsvp?id=1930040",
        "event_id": "1930040",
        "event_date": "Mon, Nov 6, 2023 1 PM  11:55 PM PST (GMT-8)",
        "event_location": "Online Event",
        "event_tags": [
            "Academic",
            "Academics",
            "OVPTL-Outreach",
            "Research"
        ]
    },
    {
        "event_name": "Interdisciplinary Research Team Application Deadline",
        "event_link": "https://campusgroups.uci.eduhttps://campusgroups.uci.edu/rsvp?id=1930038",
        "event_id": "1930038",
        "event_date": "Mon, Nov 6, 2023 1 PM  11:55 PM PST (GMT-8)",
        "event_location": "Online Event",
        "event_tags": [
            "Academic",
            "Academics",
            "OVPTL-Outreach",
            "Research"
        ]
    },
    {
        "event_name": "Narcan 101 Training",
        "event_link": "https://campusgroups.uci.eduhttps://campusgroups.uci.edu/rsvp?id=1929082",
        "event_id": "1929082",
        "event_date": "Mon, Nov 6, 2023 1 PM  2 PM PST (GMT-8)",
        "event_location": "Register with cfinazzo@uci.edu for location",
        "event_tags": [
            "Training",
            "Community",
            "Opioids",
            "Safety"
        ]
    },
    {
        "event_name": "Healthy Happenings: Communication: How to talk to professors, roommates, and parents?",
        "event_link": "https://campusgroups.uci.eduhttps://campusgroups.uci.edu/rsvp?id=1930292",
        "event_id": "1930292",
        "event_date": "Mon, Nov 6, 2023 3 PM  4 PM PST (GMT-8)",
        "event_location": "Private Location (sign in to display)",
        "event_tags": [
            "Workshop",
            "OVPTL-Workshop"
        ]
    },
    {
        "event_name": "Manoj Mitta - Caste Pride: Battles for Equality in Hindu India",
        "event_link": "https://campusgroups.uci.eduhttps://campusgroups.uci.edu/rsvp?id=1930198",
        "event_id": "1930198",
        "event_date": "Mon, Nov 6, 2023 3 PM  4 PM PST (GMT-8)",
        "event_location": "Law Building (LAW), LAW 3500",
        "event_tags": [
            "Meeting",
            "Law",
            "Law - General Public",
            "Law - HP",
            "Law - Students"
        ]
    },
    {
        "event_name": "UCDC Information Session [Hybrid]",
        "event_link": "https://campusgroups.uci.eduhttps://campusgroups.uci.edu/rsvp?id=1930311",
        "event_id": "1930311",
        "event_date": "Mon, Nov 6, 2023 3 PM  4 PM PST (GMT-8)",
        "event_location": "Student Services II Room 1020",
        "event_tags": [
            "Workshop",
            "Career",
            "Info Session",
            "Internships",
            "OVPTL-Outreach",
            "Undergrad"
        ]
    },
    {
        "event_name": "Spanish Hour",
        "event_link": "https://campusgroups.uci.eduhttps://campusgroups.uci.edu/rsvp?id=1930218",
        "event_id": "1930218",
        "event_date": "Mon, Nov 6, 2023 4 PM  5 PM PST (GMT-8)",
        "event_location": "UC Irvine Cross-Cultural Center Irvine, CA 92697-5075",
        "event_tags": [
            "Workshop",
            "Cross-Cultural Center",
            "Culture",
            "Latinx",
            "LatinxResourceCenter"
        ]
    },
    {
        "event_name": "Mindful Mondays",
        "event_link": "https://campusgroups.uci.eduhttps://campusgroups.uci.edu/rsvp?id=1929023",
        "event_id": "1929023",
        "event_date": "Mon, Nov 6, 2023 4 PM  4:30 PM PST (GMT-8)",
        "event_location": "Meet Outside Zot N' Go",
        "event_tags": [
            "Workshop",
            "Anxiety",
            "Graduate Students",
            "Meditation",
            "Mindfulness",
            "Stress Management",
            "Undergrad",
            "Wellness"
        ]
    },
    {
        "event_name": "Mid-Quarter Stress Relief & Self Care - Virtual Workshop",
        "event_link": "https://campusgroups.uci.eduhttps://campusgroups.uci.edu/rsvp?id=1930400",
        "event_id": "1930400",
        "event_date": "Mon, Nov 6, 2023 4 PM  4:30 PM PST (GMT-8)",
        "event_location": "Online Event Zoom link",
        "event_tags": [
            "Academic"
        ]
    },
    {
        "event_name": "Monday Garden Volunteer Hours (Shift 2)",
        "event_link": "https://campusgroups.uci.eduhttps://campusgroups.uci.edu/rsvp?id=1930048",
        "event_id": "1930048",
        "event_date": "Mon, Nov 6, 2023 4:30 PM  6:30 PM PST (GMT-8)",
        "event_location": "Private Location (sign in to display)",
        "event_tags": [
            "Community Service",
            "Activism",
            "Community",
            "Community Fun",
            "Community Service",
            "Empowerment",
            "Food",
            "FRESH Basic Needs Hub",
            "Gardening",
            "Nature",
            "Relaxation",
            "Social",
            "Social Ecology",
            "Social Justice",
            "Sustainability",
            "Sustainability Resource Center",
            "Traditional",
            "Volunteer",
            "Volunteer Programs",
            "Wellness"
        ]
    },
    {
        "event_name": "First-Gen Workshop: LinkedIn",
        "event_link": "https://campusgroups.uci.eduhttps://campusgroups.uci.edu/rsvp?id=1929914",
        "event_id": "1929914",
        "event_date": "Mon, Nov 6, 2023 5 PM  6 PM PST (GMT-8)",
        "event_location": "Private Location (register to display)",
        "event_tags": [
            "Workshop",
            "OVPTL-Workshop"
        ]
    },
    {
        "event_name": "Mohannad and Rana Malas Lecture in Islamic Legal Studies Presented by Sherman Jackson",
        "event_link": "https://campusgroups.uci.eduhttps://campusgroups.uci.edu/rsvp?id=1930186",
        "event_id": "1930186",
        "event_date": "Mon, Nov 6, 2023 5:30 PM  6:30 PM PST (GMT-8)",
        "event_location": "Education Building, EDU 1111",
        "event_tags": [
            "Lecture",
            "Law",
            "Law - Alumni",
            "Law - Featured",
            "Law - General Public",
            "Law - Prospective Students",
            "Law - Students",
            "Law School"
        ]
    },
    {
        "event_name": "SOAR and COVP Present: Working with Minors training",
        "event_link": "https://campusgroups.uci.eduhttps://campusgroups.uci.edu/rsvp?id=1929747",
        "event_id": "1929747",
        "event_date": "Mon, Nov 6, 2023 6:30 PM  8:30 PM PST (GMT-8)",
        "event_location": "Student Center at both Emerald Bay A and B",
        "event_tags": [
            "Workshop",
            "COVP",
            "SOAR"
        ]
    },
    {
        "event_name": "Tuesday Garden Volunteer Hours (Shift 1)",
        "event_link": "https://campusgroups.uci.eduhttps://campusgroups.uci.edu/rsvp?id=1930066",
        "event_id": "1930066",
        "event_date": "Tue, Nov 7, 2023 9 AM  12 PM PST (GMT-8)",
        "event_location": "Private Location (sign in to display)",
        "event_tags": [
            "Community Service",
            "Activism",
            "Community",
            "Community Fun",
            "Community Service",
            "Empowerment",
            "Food",
            "FRESH Basic Needs Hub",
            "Gardening",
            "Nature",
            "Relaxation",
            "Social",
            "Social Ecology",
            "Social Justice",
            "Sustainability",
            "Sustainability Resource Center",
            "Traditional",
            "Volunteer",
            "Volunteer Programs",
            "Wellness"
        ]
    },
    {
        "event_name": "Reflective Sips: First-Gen Mixer",
        "event_link": "https://campusgroups.uci.eduhttps://campusgroups.uci.edu/rsvp?id=1929868",
        "event_id": "1929868",
        "event_date": "Tue, Nov 7, 2023 10 AM  12 PM PST (GMT-8)",
        "event_location": "Private Location (sign in to display)",
        "event_tags": [
            "Workshop",
            "First Gen",
            "OVPTL-Workshop"
        ]
    },
    {
        "event_name": "Counselor in Residence",
        "event_link": "https://campusgroups.uci.eduhttps://campusgroups.uci.edu/rsvp?id=1929995",
        "event_id": "1929995",
        "event_date": "Tue, Nov 7, 2023 11 AM  12 PM PST (GMT-8)",
        "event_location": "Private Location (sign in to display)",
        "event_tags": [
            "Educational/Awareness",
            "Counseling Center",
            "UCI Counseling Center",
            "Wellness"
        ]
    }
]